{
    "parent": "code:biome/a/beach",
    "display": {
        "icon": {
            "count": 1,
            "id": "minecraft:birch_log"
        },
        "title": {
            "translate": "biome.birch_forest"
        },
        "description": {
            "translate": "empty"
        },
        "announce_to_chat": true,
        "hidden": true,
        "show_toast": true,
        "frame": "task"
    },
    "criteria": {
        "birch_forest": {
            "trigger": "minecraft:location",
            "conditions": {
                "player": {
                    "location": {
                        "biomes": "minecraft:birch_forest"
                    }
                }
            }
        }
    },
    "requirements": [
        [
            "birch_forest"
        ]
    ]
}